ubiquerg/__init__.py
ubiquerg/_version.py
ubiquerg/cli_tools.py
ubiquerg/collection.py
ubiquerg/environment.py
ubiquerg/file_locking.py
ubiquerg/files.py
ubiquerg/paths.py
ubiquerg/system.py
ubiquerg/web.py
ubiquerg-0.8.1.dist-info/LICENSE.txt
ubiquerg-0.8.1.dist-info/METADATA
ubiquerg-0.8.1.dist-info/WHEEL
ubiquerg-0.8.1.dist-info/top_level.txt
ubiquerg-0.8.1.dist-info/RECORD
